rldev/__init__.py
rldev/data.py
rldev/globv.py
rldev/image.py
rldev/pytorch.py
rldev/system.py
rldev/tools.py
rldev/workspace.py
rldev/yaml.py
rldev-0.0.4.dist-info/LICENSE
rldev-0.0.4.dist-info/METADATA
rldev-0.0.4.dist-info/WHEEL
rldev-0.0.4.dist-info/top_level.txt
rldev-0.0.4.dist-info/RECORD
