Metadata-Version: 2.1
Name: rldev
Version: 0.0.4
Summary: Kit for RL.
Home-page: https://github.com/zhangdongkun98/rl-dev
Author: Zhang Dongkun
Author-email: zhangdongkun98@gmail.com
License-File: LICENSE
